winrobot/__init__.py
winrobot/main.py
winrobot/config/__init__.py
winrobot/config/tmall.py
baozun_winrobot-0.0.5.dist-info/METADATA
baozun_winrobot-0.0.5.dist-info/WHEEL
baozun_winrobot-0.0.5.dist-info/top_level.txt
baozun_winrobot-0.0.5.dist-info/RECORD
