Metadata-Version: 2.1
Name: baozun-winrobot
Version: 0.0.5
Summary: 影刀项目
